processador_de_imagem_ptbr/__init__.py
processador_de_imagem_ptbr/processador/__init__.py
processador_de_imagem_ptbr/processador/combinacao.py
processador_de_imagem_ptbr/processador/transformacao.py
processador_de_imagem_ptbr/utilidades/__init__.py
processador_de_imagem_ptbr/utilidades/io.py
processador_de_imagem_ptbr/utilidades/plot.py
processador_de_imagem_ptbr-0.0.3.dist-info/METADATA
processador_de_imagem_ptbr-0.0.3.dist-info/WHEEL
processador_de_imagem_ptbr-0.0.3.dist-info/top_level.txt
processador_de_imagem_ptbr-0.0.3.dist-info/RECORD
