Metadata-Version: 2.1
Name: processador-de-imagem-ptbr
Version: 0.0.3
Summary: Meu pacote de processamento de imagem usando skimage
Home-page: https://github.com/AndersonGabrielCalasans/pacote-processador-de-imagem-ptbr
Author: Gabriel Calasans
Author-email: andersongabriel08@gmail.com
License: UNKNOWN
Platform: UNKNOWN
Requires-Python: >=3.8
Requires-Dist: scikit-image (>=0.16.1)
Requires-Dist: numpy
Requires-Dist: matplotlib
